mb_sql/__init__.py
mb_sql/conn.py
mb_sql/slack.py
mb_sql/snapshot.py
mb_sql/sql.py
mb_sql/tables.py
mb_sql/update.py
mb_sql/utils.py
mb_sql/version.py
mb_sql-1.0.202308151934.dist-info/METADATA
mb_sql-1.0.202308151934.dist-info/WHEEL
mb_sql-1.0.202308151934.dist-info/top_level.txt
mb_sql-1.0.202308151934.dist-info/RECORD
