Metadata-Version: 2.1
Name: mb-sql
Version: 1.0.202308151934
Summary: SQL functions package
Author: ['Malav Bateriwala']
Requires-Python: >=3.8
Requires-Dist: numpy
Requires-Dist: mb-pandas
Requires-Dist: sqlalchemy
Requires-Dist: pandas
